{
  "$schema": "https://ui.shadcn.com/schema/registry-item.json",
  "name": "v-alert-6",
  "description": "Warning Alert",
  "registryDependencies": [
    "@cnippet/alert"
  ],
  "files": [
    {
      "path": "registry/default/variants/v-alert-6.tsx",
      "content": "import { TriangleAlertIcon } from \"lucide-react\";\r\nimport {\r\n  Alert,\r\n  AlertDescription,\r\n  AlertTitle,\r\n} from \"@/registry/default/ui/alert\";\r\n\r\nexport default function Particle() {\r\n  return (\r\n    <Alert variant=\"warning\">\r\n      <TriangleAlertIcon />\r\n      <AlertTitle>Warning!</AlertTitle>\r\n      <AlertDescription>\r\n        Please check your settings. If the problem persists, contact support.\r\n      </AlertDescription>\r\n    </Alert>\r\n  );\r\n}\r\n",
      "type": "registry:block"
    }
  ],
  "meta": {
    "className": ""
  },
  "categories": [
    "alert"
  ],
  "type": "registry:block"
}