{
  "$schema": "https://ui.shadcn.com/schema/registry-item.json",
  "name": "v-calendar-18",
  "description": "Time off request with leave type selector and range picker",
  "registryDependencies": [
    "@cnippet/calendar"
  ],
  "files": [
    {
      "path": "registry/default/variants/v-calendar-18.tsx",
      "content": "\"use client\";\r\n\r\nimport * as React from \"react\";\r\nimport type { DateRange } from \"react-day-picker\";\r\nimport { Button } from \"@/registry/default/ui/button\";\r\nimport { Calendar } from \"@/registry/default/ui/calendar\";\r\n\r\nconst today = new Date();\r\n\r\nconst TIME_OFF_TYPES = [\"Vacation\", \"Sick Leave\", \"Personal\", \"Work From Home\"];\r\n\r\nexport default function Particle() {\r\n  const [range, setRange] = React.useState<DateRange | undefined>();\r\n  const [type, setType] = React.useState(\"Vacation\");\r\n  const [submitted, setSubmitted] = React.useState(false);\r\n\r\n  const days =\r\n    range?.from && range?.to\r\n      ? Math.round((range.to.getTime() - range.from.getTime()) / 86400000) + 1\r\n      : null;\r\n\r\n  function handleSubmit() {\r\n    if (!range?.from || !range?.to) return;\r\n    setSubmitted(true);\r\n    setTimeout(() => {\r\n      setSubmitted(false);\r\n      setRange(undefined);\r\n    }, 2500);\r\n  }\r\n\r\n  return (\r\n    <div className=\"flex flex-col gap-3\">\r\n      <div className=\"flex flex-wrap gap-1.5\">\r\n        {TIME_OFF_TYPES.map((t) => (\r\n          <button\r\n            className={`rounded-full border px-3 py-0.5 font-medium text-xs transition-colors ${\r\n              type === t\r\n                ? \"border-primary bg-primary text-primary-foreground\"\r\n                : \"text-muted-foreground hover:border-foreground/30\"\r\n            }`}\r\n            key={t}\r\n            onClick={() => setType(t)}\r\n            type=\"button\"\r\n          >\r\n            {t}\r\n          </button>\r\n        ))}\r\n      </div>\r\n      <Calendar\r\n        disabled={{ before: today }}\r\n        mode=\"range\"\r\n        onSelect={setRange}\r\n        selected={range}\r\n      />\r\n      <div className=\"flex items-center justify-between\">\r\n        <span className=\"text-muted-foreground text-sm\">\r\n          {days\r\n            ? `${days} day${days !== 1 ? \"s\" : \"\"} · ${type}`\r\n            : \"Select dates\"}\r\n        </span>\r\n        <Button\r\n          disabled={!range?.from || !range?.to || submitted}\r\n          onClick={handleSubmit}\r\n          size=\"sm\"\r\n        >\r\n          {submitted ? \"Submitted!\" : \"Request Time Off\"}\r\n        </Button>\r\n      </div>\r\n    </div>\r\n  );\r\n}\r\n",
      "type": "registry:block"
    }
  ],
  "meta": {
    "className": ""
  },
  "categories": [
    "calendar"
  ],
  "type": "registry:block"
}