{
  "$schema": "https://ui.shadcn.com/schema/registry-item.json",
  "name": "v-date-picker-15",
  "description": "Multi-date Availability Selector",
  "registryDependencies": [
    "@cnippet/date-picker"
  ],
  "files": [
    {
      "path": "registry/default/variants/v-date-picker-15.tsx",
      "content": "\"use client\";\r\n\r\nimport { format, isSameDay } from \"date-fns\";\r\nimport { CalendarIcon, XIcon } from \"lucide-react\";\r\nimport { useState } from \"react\";\r\nimport { Badge } from \"@/registry/default/ui/badge\";\r\nimport { Button } from \"@/registry/default/ui/button\";\r\nimport { Calendar } from \"@/registry/default/ui/calendar\";\r\nimport {\r\n  Popover,\r\n  PopoverPopup,\r\n  PopoverTrigger,\r\n} from \"@/registry/default/ui/popover\";\r\n\r\nexport default function Particle() {\r\n  const [dates, setDates] = useState<Date[]>([]);\r\n  const [open, setOpen] = useState(false);\r\n  const today = new Date();\r\n\r\n  const toggleDate = (d: Date) => {\r\n    setDates((prev) =>\r\n      prev.some((p) => isSameDay(p, d))\r\n        ? prev.filter((p) => !isSameDay(p, d))\r\n        : [...prev, d].sort((a, b) => a.getTime() - b.getTime()),\r\n    );\r\n  };\r\n\r\n  return (\r\n    <div className=\"w-full max-w-sm space-y-3\">\r\n      <div className=\"space-y-1\">\r\n        <p className=\"font-medium text-sm\">Available days</p>\r\n        <p className=\"text-muted-foreground text-xs\">\r\n          Select the days you are available for meetings.\r\n        </p>\r\n      </div>\r\n\r\n      <Popover onOpenChange={setOpen} open={open}>\r\n        <PopoverTrigger\r\n          render={<Button className=\"w-full justify-start\" variant=\"outline\" />}\r\n        >\r\n          <CalendarIcon />\r\n          {dates.length === 0\r\n            ? \"Pick available days\"\r\n            : `${dates.length} day${dates.length !== 1 ? \"s\" : \"\"} selected`}\r\n          {dates.length > 0 && (\r\n            <Badge className=\"ml-auto\" size=\"sm\" variant=\"secondary\">\r\n              {dates.length}\r\n            </Badge>\r\n          )}\r\n        </PopoverTrigger>\r\n        <PopoverPopup>\r\n          <Calendar\r\n            disabled={{ before: today }}\r\n            mode=\"multiple\"\r\n            onSelect={(days) => setDates(days ?? [])}\r\n            selected={dates}\r\n          />\r\n          <div className=\"flex justify-end gap-2 border-t p-3\">\r\n            <Button onClick={() => setDates([])} size=\"sm\" variant=\"ghost\">\r\n              Clear\r\n            </Button>\r\n            <Button onClick={() => setOpen(false)} size=\"sm\">\r\n              Done\r\n            </Button>\r\n          </div>\r\n        </PopoverPopup>\r\n      </Popover>\r\n\r\n      {dates.length > 0 && (\r\n        <div className=\"flex flex-wrap gap-1.5\">\r\n          {dates.map((d) => (\r\n            <span\r\n              className=\"flex items-center gap-1 rounded-full border bg-muted px-2.5 py-0.5 font-medium text-xs\"\r\n              key={d.toISOString()}\r\n            >\r\n              {format(d, \"MMM d\")}\r\n              <button\r\n                aria-label={`Remove ${format(d, \"MMM d\")}`}\r\n                className=\"rounded-full text-muted-foreground hover:text-foreground\"\r\n                onClick={() => toggleDate(d)}\r\n                type=\"button\"\r\n              >\r\n                <XIcon className=\"size-3\" />\r\n              </button>\r\n            </span>\r\n          ))}\r\n        </div>\r\n      )}\r\n    </div>\r\n  );\r\n}\r\n",
      "type": "registry:block"
    }
  ],
  "meta": {
    "className": ""
  },
  "categories": [
    "date picker"
  ],
  "type": "registry:block"
}