{
  "$schema": "https://ui.shadcn.com/schema/registry-item.json",
  "name": "v-date-picker-4",
  "description": "Basic date picker",
  "registryDependencies": [
    "@cnippet/date-picker"
  ],
  "files": [
    {
      "path": "registry/default/variants/v-date-picker-4.tsx",
      "content": "export default function Component() {\r\n  return <div>Date Picker</div>;\r\n}\r\n",
      "type": "registry:block"
    }
  ],
  "meta": {
    "className": ""
  },
  "categories": [
    "date picker"
  ],
  "type": "registry:block"
}