{
  "$schema": "https://ui.shadcn.com/schema/registry-item.json",
  "name": "v-input-20",
  "description": "Basic password strength with dynamic hint and icons",
  "registryDependencies": [
    "@cnippet/input"
  ],
  "files": [
    {
      "path": "registry/default/variants/v-input-20.tsx",
      "content": "\"use client\";\r\n\r\nimport { AlertTriangleIcon, CircleCheckIcon, InfoIcon } from \"lucide-react\";\r\nimport { useId, useState } from \"react\";\r\nimport { cn } from \"@/lib/utils\";\r\nimport { Field, FieldLabel } from \"@/registry/default/ui/field\";\r\nimport { Input } from \"@/registry/default/ui/input\";\r\n\r\nexport function Pattern() {\r\n  const id = useId();\r\n  const [password, setPassword] = useState(\"\");\r\n\r\n  const getStrength = (pass: string) => {\r\n    const requirements = [\r\n      { met: pass.length >= 8, text: \"8+ characters\" },\r\n      { met: /[0-9]/.test(pass), text: \"a number\" },\r\n      { met: /[!@#$%^&*]/.test(pass), text: \"a special character\" },\r\n    ];\r\n    const metCount = requirements.filter((r) => r.met).length;\r\n    return { metCount, requirements };\r\n  };\r\n\r\n  const { metCount } = getStrength(password);\r\n\r\n  const getHint = () => {\r\n    if (!password) {\r\n      return \"Use 8+ characters with a number and a special character.\";\r\n    }\r\n    if (metCount === 3) {\r\n      return \"Strong password. You're all set!\";\r\n    }\r\n    if (metCount === 2) {\r\n      return \"Almost there! Add the missing requirement.\";\r\n    }\r\n    return \"Weak password. Include 8+ characters, a number, and a special character.\";\r\n  };\r\n\r\n  const getStatus = () => {\r\n    if (!password)\r\n      return {\r\n        color: \"text-muted-foreground\",\r\n        icon: <InfoIcon className=\"size-3.5 shrink-0\" />,\r\n      };\r\n    if (metCount === 3)\r\n      return {\r\n        color: \"text-emerald-500\",\r\n        icon: <CircleCheckIcon className=\"size-3.5 shrink-0\" />,\r\n      };\r\n    if (metCount === 2)\r\n      return {\r\n        color: \"text-amber-500\",\r\n        icon: <AlertTriangleIcon className=\"size-3.5 shrink-0\" />,\r\n      };\r\n    return {\r\n      color: \"text-destructive\",\r\n      icon: <AlertTriangleIcon className=\"size-3.5 shrink-0\" />,\r\n    };\r\n  };\r\n\r\n  const { color, icon: StatusIcon } = getStatus();\r\n\r\n  return (\r\n    <Field className=\"w-full max-w-xs\">\r\n      <FieldLabel htmlFor={id}>Password</FieldLabel>\r\n      <Input\r\n        id={id}\r\n        onChange={(e) => setPassword(e.target.value)}\r\n        placeholder=\"Enter password\"\r\n        type=\"password\"\r\n        value={password}\r\n      />\r\n      <div\r\n        className={cn(\r\n          \"flex items-center gap-2 text-xs transition-colors duration-200\",\r\n          color,\r\n        )}\r\n      >\r\n        {StatusIcon}\r\n        <p>{getHint()}</p>\r\n      </div>\r\n    </Field>\r\n  );\r\n}\r\n",
      "type": "registry:block"
    }
  ],
  "meta": {
    "className": ""
  },
  "categories": [
    "input"
  ],
  "type": "registry:block"
}