{
  "$schema": "https://ui.shadcn.com/schema/registry-item.json",
  "name": "v-popover-9",
  "description": "Quick Settings",
  "registryDependencies": [
    "@cnippet/popover"
  ],
  "files": [
    {
      "path": "registry/default/variants/v-popover-9.tsx",
      "content": "\"use client\";\r\n\r\nimport { ArrowLeftIcon, ArrowRightIcon, CompassIcon } from \"lucide-react\";\r\nimport { useState } from \"react\";\r\nimport { Button } from \"@/registry/default/ui/button\";\r\nimport {\r\n  Popover,\r\n  PopoverContent,\r\n  PopoverTrigger,\r\n} from \"@/registry/default/ui/popover\";\r\n\r\nconst steps = [\r\n  {\r\n    description:\r\n      \"Add team members by email to collaborate on projects in real time. Assign roles and manage permissions from the team settings.\",\r\n    title: \"Invite Your Team\",\r\n  },\r\n  {\r\n    description:\r\n      \"Set up your first project with a name, description, and timeline. Choose from templates or start from scratch.\",\r\n    title: \"Create a Project\",\r\n  },\r\n  {\r\n    description:\r\n      \"Link tools like GitHub, Slack, and Figma to streamline your workflow and keep everything in sync.\",\r\n    title: \"Connect Integrations\",\r\n  },\r\n  {\r\n    description:\r\n      \"Customize which events trigger alerts — mentions, due dates, status changes, and deployment updates.\",\r\n    title: \"Set Up Notifications\",\r\n  },\r\n];\r\n\r\nexport function Pattern() {\r\n  const [currentStep, setCurrentStep] = useState(0);\r\n\r\n  const handleNext = () => {\r\n    if (currentStep < steps.length - 1) {\r\n      setCurrentStep(currentStep + 1);\r\n    }\r\n  };\r\n\r\n  const handlePrev = () => {\r\n    if (currentStep > 0) {\r\n      setCurrentStep(currentStep - 1);\r\n    }\r\n  };\r\n\r\n  const isFirst = currentStep === 0;\r\n  const isLast = currentStep === steps.length - 1;\r\n\r\n  return (\r\n    <div className=\"flex min-h-25 items-center justify-center\">\r\n      <Popover>\r\n        <PopoverTrigger render={<Button variant=\"outline\" />}>\r\n          <CompassIcon aria-hidden=\"true\" />\r\n          Feature Tour\r\n        </PopoverTrigger>\r\n        <PopoverContent\r\n          className=\"w-72 gap-2 px-3 pt-3 pb-2\"\r\n          side=\"top\"\r\n          sideOffset={8}\r\n        >\r\n          <div className=\"space-y-2\">\r\n            <p className=\"font-medium leading-tight\">\r\n              {steps[currentStep]?.title}\r\n            </p>\r\n            <p className=\"text-muted-foreground\">\r\n              {steps[currentStep]?.description}\r\n            </p>\r\n          </div>\r\n          <div className=\"flex items-center justify-between\">\r\n            <span className=\"text-muted-foreground\">\r\n              {currentStep + 1} of {steps.length}\r\n            </span>\r\n            <div className=\"flex gap-0.5\">\r\n              <Button\r\n                aria-label=\"Previous step\"\r\n                className=\"size-6\"\r\n                disabled={isFirst}\r\n                onClick={handlePrev}\r\n                size=\"icon\"\r\n                variant=\"ghost\"\r\n              >\r\n                <ArrowLeftIcon aria-hidden=\"true\" className=\"size-3.5\" />\r\n              </Button>\r\n              <Button\r\n                aria-label=\"Next step\"\r\n                className=\"size-6\"\r\n                disabled={isLast}\r\n                onClick={handleNext}\r\n                size=\"icon\"\r\n                variant=\"ghost\"\r\n              >\r\n                <ArrowRightIcon aria-hidden=\"true\" className=\"size-3.5\" />\r\n              </Button>\r\n            </div>\r\n          </div>\r\n        </PopoverContent>\r\n      </Popover>\r\n    </div>\r\n  );\r\n}\r\n",
      "type": "registry:block"
    }
  ],
  "meta": {
    "className": ""
  },
  "categories": [
    "popover"
  ],
  "type": "registry:block"
}