{
  "$schema": "https://ui.shadcn.com/schema/registry-item.json",
  "name": "v-switch-4",
  "description": "Switch group",
  "registryDependencies": [
    "@cnippet/switch"
  ],
  "files": [
    {
      "path": "registry/default/variants/v-switch-4.tsx",
      "content": "import { Field, FieldLabel } from \"@/registry/default/ui//field\";\r\nimport { Switch } from \"@/registry/default/ui//switch\";\r\n\r\nexport function Pattern() {\r\n  return (\r\n    <Field className=\"w-auto space-y-2\">\r\n      <FieldLabel>Notification Settings</FieldLabel>\r\n      <Field className=\"flex-row\">\r\n        <Switch defaultChecked id=\"sg-email\" />\r\n        <FieldLabel htmlFor=\"sg-email\">Email notifications</FieldLabel>\r\n      </Field>\r\n      <Field className=\"flex-row\">\r\n        <Switch id=\"sg-sms\" />\r\n        <FieldLabel htmlFor=\"sg-sms\">SMS notifications</FieldLabel>\r\n      </Field>\r\n      <Field className=\"flex-row\">\r\n        <Switch defaultChecked id=\"sg-push\" />\r\n        <FieldLabel htmlFor=\"sg-push\">Push notifications</FieldLabel>\r\n      </Field>\r\n    </Field>\r\n  );\r\n}\r\n",
      "type": "registry:block"
    }
  ],
  "meta": {
    "className": ""
  },
  "categories": [
    "switch"
  ],
  "type": "registry:block"
}